<?xml version="1.0" ?>
<FlowMonitor>
  <FlowStats>
    <Flow flowId="1" timeFirstTxPacket="+3.56082e+10ns" timeFirstRxPacket="+3.56683e+10ns" timeLastTxPacket="+6.83967e+10ns" timeLastRxPacket="+6.26341e+10ns" delaySum="+7.21819e+11ns" jitterSum="+6.24964e+09ns" lastDelay="+2.2992e+08ns" maxDelay="+7.03921e+08ns" minDelay="+2.40932e+06ns" txBytes="3476520" rxBytes="1258200" txPackets="6438" rxPackets="2330" lostPackets="2638" timesForwarded="5305">
      <packetsDropped reasonCode="0" number="30" />
      <bytesDropped reasonCode="0" bytes="16200" />
      <delayHistogram nBins="704" >
        <bin index="2" start="0.002" width="0.001" count="541" />
        <bin index="3" start="0.003" width="0.001" count="35" />
        <bin index="4" start="0.004" width="0.001" count="44" />
        <bin index="5" start="0.005" width="0.001" count="5" />
        <bin index="6" start="0.006" width="0.001" count="8" />
        <bin index="7" start="0.007" width="0.001" count="7" />
        <bin index="8" start="0.008" width="0.001" count="3" />
        <bin index="9" start="0.009" width="0.001" count="2" />
        <bin index="10" start="0.01" width="0.001" count="14" />
        <bin index="11" start="0.011" width="0.001" count="17" />
        <bin index="12" start="0.012" width="0.001" count="8" />
        <bin index="13" start="0.013" width="0.001" count="7" />
        <bin index="14" start="0.014" width="0.001" count="24" />
        <bin index="15" start="0.015" width="0.001" count="21" />
        <bin index="16" start="0.016" width="0.001" count="4" />
        <bin index="17" start="0.017" width="0.001" count="3" />
        <bin index="18" start="0.018" width="0.001" count="3" />
        <bin index="19" start="0.019" width="0.001" count="1" />
        <bin index="20" start="0.02" width="0.001" count="3" />
        <bin index="21" start="0.021" width="0.001" count="2" />
        <bin index="22" start="0.022" width="0.001" count="2" />
        <bin index="23" start="0.023" width="0.001" count="1" />
        <bin index="24" start="0.024" width="0.001" count="1" />
        <bin index="25" start="0.025" width="0.001" count="1" />
        <bin index="26" start="0.026" width="0.001" count="1" />
        <bin index="27" start="0.027" width="0.001" count="2" />
        <bin index="28" start="0.028" width="0.001" count="1" />
        <bin index="30" start="0.03" width="0.001" count="1" />
        <bin index="32" start="0.032" width="0.001" count="1" />
        <bin index="35" start="0.035" width="0.001" count="1" />
        <bin index="36" start="0.036" width="0.001" count="1" />
        <bin index="40" start="0.04" width="0.001" count="1" />
        <bin index="41" start="0.041" width="0.001" count="1" />
        <bin index="43" start="0.043" width="0.001" count="1" />
        <bin index="45" start="0.045" width="0.001" count="1" />
        <bin index="48" start="0.048" width="0.001" count="1" />
        <bin index="51" start="0.051" width="0.001" count="3" />
        <bin index="52" start="0.052" width="0.001" count="1" />
        <bin index="54" start="0.054" width="0.001" count="3" />
        <bin index="56" start="0.056" width="0.001" count="1" />
        <bin index="57" start="0.057" width="0.001" count="4" />
        <bin index="58" start="0.058" width="0.001" count="2" />
        <bin index="59" start="0.059" width="0.001" count="1" />
        <bin index="60" start="0.06" width="0.001" count="2" />
        <bin index="62" start="0.062" width="0.001" count="1" />
        <bin index="63" start="0.063" width="0.001" count="2" />
        <bin index="66" start="0.066" width="0.001" count="1" />
        <bin index="69" start="0.069" width="0.001" count="1" />
        <bin index="71" start="0.071" width="0.001" count="1" />
        <bin index="72" start="0.072" width="0.001" count="2" />
        <bin index="74" start="0.074" width="0.001" count="2" />
        <bin index="78" start="0.078" width="0.001" count="1" />
        <bin index="91" start="0.091" width="0.001" count="1" />
        <bin index="97" start="0.097" width="0.001" count="1" />
        <bin index="98" start="0.098" width="0.001" count="1" />
        <bin index="99" start="0.099" width="0.001" count="1" />
        <bin index="100" start="0.1" width="0.001" count="1" />
        <bin index="110" start="0.11" width="0.001" count="1" />
        <bin index="113" start="0.113" width="0.001" count="1" />
        <bin index="114" start="0.114" width="0.001" count="1" />
        <bin index="115" start="0.115" width="0.001" count="1" />
        <bin index="118" start="0.118" width="0.001" count="4" />
        <bin index="119" start="0.119" width="0.001" count="2" />
        <bin index="121" start="0.121" width="0.001" count="1" />
        <bin index="122" start="0.122" width="0.001" count="2" />
        <bin index="124" start="0.124" width="0.001" count="3" />
        <bin index="125" start="0.125" width="0.001" count="2" />
        <bin index="126" start="0.126" width="0.001" count="1" />
        <bin index="127" start="0.127" width="0.001" count="1" />
        <bin index="129" start="0.129" width="0.001" count="3" />
        <bin index="130" start="0.13" width="0.001" count="1" />
        <bin index="131" start="0.131" width="0.001" count="1" />
        <bin index="132" start="0.132" width="0.001" count="2" />
        <bin index="134" start="0.134" width="0.001" count="3" />
        <bin index="135" start="0.135" width="0.001" count="2" />
        <bin index="137" start="0.137" width="0.001" count="2" />
        <bin index="138" start="0.138" width="0.001" count="1" />
        <bin index="139" start="0.139" width="0.001" count="1" />
        <bin index="140" start="0.14" width="0.001" count="1" />
        <bin index="141" start="0.141" width="0.001" count="1" />
        <bin index="142" start="0.142" width="0.001" count="1" />
        <bin index="144" start="0.144" width="0.001" count="1" />
        <bin index="147" start="0.147" width="0.001" count="2" />
        <bin index="148" start="0.148" width="0.001" count="1" />
        <bin index="149" start="0.149" width="0.001" count="1" />
        <bin index="150" start="0.15" width="0.001" count="1" />
        <bin index="151" start="0.151" width="0.001" count="1" />
        <bin index="152" start="0.152" width="0.001" count="2" />
        <bin index="153" start="0.153" width="0.001" count="3" />
        <bin index="154" start="0.154" width="0.001" count="1" />
        <bin index="155" start="0.155" width="0.001" count="1" />
        <bin index="157" start="0.157" width="0.001" count="1" />
        <bin index="158" start="0.158" width="0.001" count="1" />
        <bin index="159" start="0.159" width="0.001" count="1" />
        <bin index="160" start="0.16" width="0.001" count="2" />
        <bin index="161" start="0.161" width="0.001" count="2" />
        <bin index="163" start="0.163" width="0.001" count="1" />
        <bin index="165" start="0.165" width="0.001" count="1" />
        <bin index="166" start="0.166" width="0.001" count="1" />
        <bin index="168" start="0.168" width="0.001" count="1" />
        <bin index="169" start="0.169" width="0.001" count="2" />
        <bin index="170" start="0.17" width="0.001" count="3" />
        <bin index="171" start="0.171" width="0.001" count="1" />
        <bin index="172" start="0.172" width="0.001" count="1" />
        <bin index="174" start="0.174" width="0.001" count="2" />
        <bin index="176" start="0.176" width="0.001" count="1" />
        <bin index="177" start="0.177" width="0.001" count="1" />
        <bin index="179" start="0.179" width="0.001" count="1" />
        <bin index="180" start="0.18" width="0.001" count="1" />
        <bin index="182" start="0.182" width="0.001" count="1" />
        <bin index="183" start="0.183" width="0.001" count="1" />
        <bin index="186" start="0.186" width="0.001" count="2" />
        <bin index="187" start="0.187" width="0.001" count="1" />
        <bin index="190" start="0.19" width="0.001" count="1" />
        <bin index="192" start="0.192" width="0.001" count="1" />
        <bin index="193" start="0.193" width="0.001" count="1" />
        <bin index="194" start="0.194" width="0.001" count="1" />
        <bin index="195" start="0.195" width="0.001" count="1" />
        <bin index="196" start="0.196" width="0.001" count="2" />
        <bin index="197" start="0.197" width="0.001" count="1" />
        <bin index="198" start="0.198" width="0.001" count="2" />
        <bin index="201" start="0.201" width="0.001" count="1" />
        <bin index="203" start="0.203" width="0.001" count="1" />
        <bin index="205" start="0.205" width="0.001" count="1" />
        <bin index="206" start="0.206" width="0.001" count="1" />
        <bin index="208" start="0.208" width="0.001" count="1" />
        <bin index="211" start="0.211" width="0.001" count="1" />
        <bin index="219" start="0.219" width="0.001" count="1" />
        <bin index="220" start="0.22" width="0.001" count="1" />
        <bin index="221" start="0.221" width="0.001" count="1" />
        <bin index="223" start="0.223" width="0.001" count="1" />
        <bin index="226" start="0.226" width="0.001" count="1" />
        <bin index="229" start="0.229" width="0.001" count="2" />
        <bin index="232" start="0.232" width="0.001" count="1" />
        <bin index="238" start="0.238" width="0.001" count="1" />
        <bin index="245" start="0.245" width="0.001" count="2" />
        <bin index="246" start="0.246" width="0.001" count="1" />
        <bin index="247" start="0.247" width="0.001" count="2" />
        <bin index="255" start="0.255" width="0.001" count="1" />
        <bin index="256" start="0.256" width="0.001" count="1" />
        <bin index="257" start="0.257" width="0.001" count="1" />
        <bin index="258" start="0.258" width="0.001" count="1" />
        <bin index="281" start="0.281" width="0.001" count="1" />
        <bin index="376" start="0.376" width="0.001" count="1" />
        <bin index="377" start="0.377" width="0.001" count="1" />
        <bin index="378" start="0.378" width="0.001" count="2" />
        <bin index="379" start="0.379" width="0.001" count="1" />
        <bin index="381" start="0.381" width="0.001" count="1" />
        <bin index="383" start="0.383" width="0.001" count="1" />
        <bin index="385" start="0.385" width="0.001" count="1" />
        <bin index="386" start="0.386" width="0.001" count="2" />
        <bin index="387" start="0.387" width="0.001" count="5" />
        <bin index="388" start="0.388" width="0.001" count="5" />
        <bin index="389" start="0.389" width="0.001" count="5" />
        <bin index="390" start="0.39" width="0.001" count="6" />
        <bin index="391" start="0.391" width="0.001" count="5" />
        <bin index="392" start="0.392" width="0.001" count="3" />
        <bin index="393" start="0.393" width="0.001" count="2" />
        <bin index="394" start="0.394" width="0.001" count="3" />
        <bin index="395" start="0.395" width="0.001" count="3" />
        <bin index="396" start="0.396" width="0.001" count="2" />
        <bin index="397" start="0.397" width="0.001" count="4" />
        <bin index="398" start="0.398" width="0.001" count="9" />
        <bin index="399" start="0.399" width="0.001" count="11" />
        <bin index="400" start="0.4" width="0.001" count="20" />
        <bin index="401" start="0.401" width="0.001" count="17" />
        <bin index="402" start="0.402" width="0.001" count="16" />
        <bin index="403" start="0.403" width="0.001" count="16" />
        <bin index="404" start="0.404" width="0.001" count="10" />
        <bin index="405" start="0.405" width="0.001" count="14" />
        <bin index="406" start="0.406" width="0.001" count="20" />
        <bin index="407" start="0.407" width="0.001" count="19" />
        <bin index="408" start="0.408" width="0.001" count="30" />
        <bin index="409" start="0.409" width="0.001" count="26" />
        <bin index="410" start="0.41" width="0.001" count="28" />
        <bin index="411" start="0.411" width="0.001" count="16" />
        <bin index="412" start="0.412" width="0.001" count="10" />
        <bin index="413" start="0.413" width="0.001" count="5" />
        <bin index="414" start="0.414" width="0.001" count="10" />
        <bin index="415" start="0.415" width="0.001" count="9" />
        <bin index="416" start="0.416" width="0.001" count="8" />
        <bin index="417" start="0.417" width="0.001" count="13" />
        <bin index="418" start="0.418" width="0.001" count="10" />
        <bin index="419" start="0.419" width="0.001" count="8" />
        <bin index="420" start="0.42" width="0.001" count="10" />
        <bin index="421" start="0.421" width="0.001" count="4" />
        <bin index="422" start="0.422" width="0.001" count="2" />
        <bin index="423" start="0.423" width="0.001" count="2" />
        <bin index="424" start="0.424" width="0.001" count="3" />
        <bin index="425" start="0.425" width="0.001" count="4" />
        <bin index="426" start="0.426" width="0.001" count="2" />
        <bin index="427" start="0.427" width="0.001" count="1" />
        <bin index="428" start="0.428" width="0.001" count="2" />
        <bin index="429" start="0.429" width="0.001" count="1" />
        <bin index="430" start="0.43" width="0.001" count="1" />
        <bin index="431" start="0.431" width="0.001" count="2" />
        <bin index="432" start="0.432" width="0.001" count="1" />
        <bin index="433" start="0.433" width="0.001" count="1" />
        <bin index="435" start="0.435" width="0.001" count="1" />
        <bin index="437" start="0.437" width="0.001" count="2" />
        <bin index="439" start="0.439" width="0.001" count="1" />
        <bin index="440" start="0.44" width="0.001" count="1" />
        <bin index="442" start="0.442" width="0.001" count="2" />
        <bin index="443" start="0.443" width="0.001" count="2" />
        <bin index="444" start="0.444" width="0.001" count="1" />
        <bin index="445" start="0.445" width="0.001" count="2" />
        <bin index="446" start="0.446" width="0.001" count="1" />
        <bin index="447" start="0.447" width="0.001" count="1" />
        <bin index="449" start="0.449" width="0.001" count="2" />
        <bin index="451" start="0.451" width="0.001" count="1" />
        <bin index="454" start="0.454" width="0.001" count="1" />
        <bin index="457" start="0.457" width="0.001" count="1" />
        <bin index="459" start="0.459" width="0.001" count="1" />
        <bin index="461" start="0.461" width="0.001" count="1" />
        <bin index="462" start="0.462" width="0.001" count="1" />
        <bin index="463" start="0.463" width="0.001" count="1" />
        <bin index="464" start="0.464" width="0.001" count="2" />
        <bin index="467" start="0.467" width="0.001" count="1" />
        <bin index="470" start="0.47" width="0.001" count="1" />
        <bin index="471" start="0.471" width="0.001" count="1" />
        <bin index="472" start="0.472" width="0.001" count="1" />
        <bin index="476" start="0.476" width="0.001" count="1" />
        <bin index="478" start="0.478" width="0.001" count="2" />
        <bin index="481" start="0.481" width="0.001" count="1" />
        <bin index="483" start="0.483" width="0.001" count="1" />
        <bin index="486" start="0.486" width="0.001" count="1" />
        <bin index="487" start="0.487" width="0.001" count="2" />
        <bin index="488" start="0.488" width="0.001" count="1" />
        <bin index="489" start="0.489" width="0.001" count="3" />
        <bin index="490" start="0.49" width="0.001" count="1" />
        <bin index="491" start="0.491" width="0.001" count="2" />
        <bin index="492" start="0.492" width="0.001" count="7" />
        <bin index="493" start="0.493" width="0.001" count="10" />
        <bin index="494" start="0.494" width="0.001" count="12" />
        <bin index="495" start="0.495" width="0.001" count="6" />
        <bin index="496" start="0.496" width="0.001" count="27" />
        <bin index="497" start="0.497" width="0.001" count="31" />
        <bin index="498" start="0.498" width="0.001" count="58" />
        <bin index="499" start="0.499" width="0.001" count="73" />
        <bin index="500" start="0.5" width="0.001" count="61" />
        <bin index="501" start="0.501" width="0.001" count="70" />
        <bin index="502" start="0.502" width="0.001" count="44" />
        <bin index="503" start="0.503" width="0.001" count="24" />
        <bin index="504" start="0.504" width="0.001" count="17" />
        <bin index="505" start="0.505" width="0.001" count="15" />
        <bin index="506" start="0.506" width="0.001" count="11" />
        <bin index="507" start="0.507" width="0.001" count="10" />
        <bin index="508" start="0.508" width="0.001" count="11" />
        <bin index="509" start="0.509" width="0.001" count="5" />
        <bin index="510" start="0.51" width="0.001" count="7" />
        <bin index="511" start="0.511" width="0.001" count="8" />
        <bin index="512" start="0.512" width="0.001" count="8" />
        <bin index="513" start="0.513" width="0.001" count="3" />
        <bin index="514" start="0.514" width="0.001" count="9" />
        <bin index="515" start="0.515" width="0.001" count="11" />
        <bin index="516" start="0.516" width="0.001" count="2" />
        <bin index="517" start="0.517" width="0.001" count="4" />
        <bin index="518" start="0.518" width="0.001" count="6" />
        <bin index="519" start="0.519" width="0.001" count="3" />
        <bin index="520" start="0.52" width="0.001" count="6" />
        <bin index="521" start="0.521" width="0.001" count="4" />
        <bin index="522" start="0.522" width="0.001" count="1" />
        <bin index="523" start="0.523" width="0.001" count="4" />
        <bin index="524" start="0.524" width="0.001" count="5" />
        <bin index="525" start="0.525" width="0.001" count="3" />
        <bin index="526" start="0.526" width="0.001" count="7" />
        <bin index="527" start="0.527" width="0.001" count="4" />
        <bin index="528" start="0.528" width="0.001" count="3" />
        <bin index="529" start="0.529" width="0.001" count="7" />
        <bin index="530" start="0.53" width="0.001" count="4" />
        <bin index="531" start="0.531" width="0.001" count="2" />
        <bin index="532" start="0.532" width="0.001" count="4" />
        <bin index="533" start="0.533" width="0.001" count="5" />
        <bin index="534" start="0.534" width="0.001" count="3" />
        <bin index="535" start="0.535" width="0.001" count="6" />
        <bin index="536" start="0.536" width="0.001" count="2" />
        <bin index="537" start="0.537" width="0.001" count="4" />
        <bin index="538" start="0.538" width="0.001" count="5" />
        <bin index="539" start="0.539" width="0.001" count="4" />
        <bin index="540" start="0.54" width="0.001" count="4" />
        <bin index="541" start="0.541" width="0.001" count="4" />
        <bin index="542" start="0.542" width="0.001" count="4" />
        <bin index="543" start="0.543" width="0.001" count="4" />
        <bin index="544" start="0.544" width="0.001" count="4" />
        <bin index="545" start="0.545" width="0.001" count="3" />
        <bin index="546" start="0.546" width="0.001" count="6" />
        <bin index="547" start="0.547" width="0.001" count="3" />
        <bin index="548" start="0.548" width="0.001" count="4" />
        <bin index="549" start="0.549" width="0.001" count="5" />
        <bin index="550" start="0.55" width="0.001" count="4" />
        <bin index="551" start="0.551" width="0.001" count="6" />
        <bin index="552" start="0.552" width="0.001" count="3" />
        <bin index="553" start="0.553" width="0.001" count="5" />
        <bin index="554" start="0.554" width="0.001" count="2" />
        <bin index="555" start="0.555" width="0.001" count="3" />
        <bin index="556" start="0.556" width="0.001" count="5" />
        <bin index="557" start="0.557" width="0.001" count="4" />
        <bin index="558" start="0.558" width="0.001" count="5" />
        <bin index="559" start="0.559" width="0.001" count="1" />
        <bin index="560" start="0.56" width="0.001" count="5" />
        <bin index="561" start="0.561" width="0.001" count="6" />
        <bin index="562" start="0.562" width="0.001" count="2" />
        <bin index="563" start="0.563" width="0.001" count="3" />
        <bin index="564" start="0.564" width="0.001" count="5" />
        <bin index="565" start="0.565" width="0.001" count="3" />
        <bin index="566" start="0.566" width="0.001" count="4" />
        <bin index="567" start="0.567" width="0.001" count="5" />
        <bin index="568" start="0.568" width="0.001" count="3" />
        <bin index="569" start="0.569" width="0.001" count="2" />
        <bin index="570" start="0.57" width="0.001" count="5" />
        <bin index="571" start="0.571" width="0.001" count="3" />
        <bin index="572" start="0.572" width="0.001" count="2" />
        <bin index="573" start="0.573" width="0.001" count="3" />
        <bin index="574" start="0.574" width="0.001" count="2" />
        <bin index="575" start="0.575" width="0.001" count="4" />
        <bin index="576" start="0.576" width="0.001" count="2" />
        <bin index="577" start="0.577" width="0.001" count="3" />
        <bin index="578" start="0.578" width="0.001" count="4" />
        <bin index="579" start="0.579" width="0.001" count="4" />
        <bin index="580" start="0.58" width="0.001" count="4" />
        <bin index="581" start="0.581" width="0.001" count="4" />
        <bin index="582" start="0.582" width="0.001" count="4" />
        <bin index="583" start="0.583" width="0.001" count="4" />
        <bin index="584" start="0.584" width="0.001" count="2" />
        <bin index="585" start="0.585" width="0.001" count="5" />
        <bin index="586" start="0.586" width="0.001" count="2" />
        <bin index="587" start="0.587" width="0.001" count="6" />
        <bin index="588" start="0.588" width="0.001" count="7" />
        <bin index="589" start="0.589" width="0.001" count="3" />
        <bin index="590" start="0.59" width="0.001" count="6" />
        <bin index="591" start="0.591" width="0.001" count="4" />
        <bin index="592" start="0.592" width="0.001" count="5" />
        <bin index="593" start="0.593" width="0.001" count="2" />
        <bin index="594" start="0.594" width="0.001" count="2" />
        <bin index="595" start="0.595" width="0.001" count="7" />
        <bin index="596" start="0.596" width="0.001" count="4" />
        <bin index="597" start="0.597" width="0.001" count="5" />
        <bin index="598" start="0.598" width="0.001" count="3" />
        <bin index="599" start="0.599" width="0.001" count="3" />
        <bin index="600" start="0.6" width="0.001" count="2" />
        <bin index="601" start="0.601" width="0.001" count="5" />
        <bin index="602" start="0.602" width="0.001" count="3" />
        <bin index="604" start="0.604" width="0.001" count="5" />
        <bin index="605" start="0.605" width="0.001" count="1" />
        <bin index="607" start="0.607" width="0.001" count="5" />
        <bin index="608" start="0.608" width="0.001" count="1" />
        <bin index="609" start="0.609" width="0.001" count="1" />
        <bin index="610" start="0.61" width="0.001" count="4" />
        <bin index="612" start="0.612" width="0.001" count="1" />
        <bin index="613" start="0.613" width="0.001" count="2" />
        <bin index="614" start="0.614" width="0.001" count="2" />
        <bin index="615" start="0.615" width="0.001" count="3" />
        <bin index="616" start="0.616" width="0.001" count="1" />
        <bin index="617" start="0.617" width="0.001" count="2" />
        <bin index="619" start="0.619" width="0.001" count="4" />
        <bin index="620" start="0.62" width="0.001" count="1" />
        <bin index="621" start="0.621" width="0.001" count="3" />
        <bin index="622" start="0.622" width="0.001" count="3" />
        <bin index="623" start="0.623" width="0.001" count="1" />
        <bin index="625" start="0.625" width="0.001" count="2" />
        <bin index="627" start="0.627" width="0.001" count="1" />
        <bin index="628" start="0.628" width="0.001" count="2" />
        <bin index="629" start="0.629" width="0.001" count="1" />
        <bin index="631" start="0.631" width="0.001" count="2" />
        <bin index="633" start="0.633" width="0.001" count="2" />
        <bin index="635" start="0.635" width="0.001" count="1" />
        <bin index="638" start="0.638" width="0.001" count="2" />
        <bin index="639" start="0.639" width="0.001" count="1" />
        <bin index="641" start="0.641" width="0.001" count="1" />
        <bin index="643" start="0.643" width="0.001" count="1" />
        <bin index="648" start="0.648" width="0.001" count="1" />
        <bin index="649" start="0.649" width="0.001" count="1" />
        <bin index="650" start="0.65" width="0.001" count="3" />
        <bin index="652" start="0.652" width="0.001" count="2" />
        <bin index="671" start="0.671" width="0.001" count="1" />
        <bin index="676" start="0.676" width="0.001" count="1" />
        <bin index="678" start="0.678" width="0.001" count="2" />
        <bin index="679" start="0.679" width="0.001" count="1" />
        <bin index="682" start="0.682" width="0.001" count="1" />
        <bin index="684" start="0.684" width="0.001" count="1" />
        <bin index="686" start="0.686" width="0.001" count="1" />
        <bin index="689" start="0.689" width="0.001" count="1" />
        <bin index="701" start="0.701" width="0.001" count="1" />
        <bin index="702" start="0.702" width="0.001" count="1" />
        <bin index="703" start="0.703" width="0.001" count="1" />
      </delayHistogram>
      <jitterHistogram nBins="386" >
        <bin index="0" start="0" width="0.001" count="1230" />
        <bin index="1" start="0.001" width="0.001" count="326" />
        <bin index="2" start="0.002" width="0.001" count="389" />
        <bin index="3" start="0.003" width="0.001" count="223" />
        <bin index="4" start="0.004" width="0.001" count="25" />
        <bin index="5" start="0.005" width="0.001" count="24" />
        <bin index="6" start="0.006" width="0.001" count="15" />
        <bin index="7" start="0.007" width="0.001" count="13" />
        <bin index="8" start="0.008" width="0.001" count="6" />
        <bin index="9" start="0.009" width="0.001" count="3" />
        <bin index="10" start="0.01" width="0.001" count="6" />
        <bin index="11" start="0.011" width="0.001" count="5" />
        <bin index="12" start="0.012" width="0.001" count="2" />
        <bin index="13" start="0.013" width="0.001" count="2" />
        <bin index="14" start="0.014" width="0.001" count="2" />
        <bin index="15" start="0.015" width="0.001" count="1" />
        <bin index="16" start="0.016" width="0.001" count="1" />
        <bin index="17" start="0.017" width="0.001" count="5" />
        <bin index="18" start="0.018" width="0.001" count="1" />
        <bin index="20" start="0.02" width="0.001" count="5" />
        <bin index="21" start="0.021" width="0.001" count="2" />
        <bin index="22" start="0.022" width="0.001" count="2" />
        <bin index="23" start="0.023" width="0.001" count="1" />
        <bin index="25" start="0.025" width="0.001" count="2" />
        <bin index="26" start="0.026" width="0.001" count="2" />
        <bin index="28" start="0.028" width="0.001" count="1" />
        <bin index="29" start="0.029" width="0.001" count="3" />
        <bin index="32" start="0.032" width="0.001" count="2" />
        <bin index="35" start="0.035" width="0.001" count="1" />
        <bin index="38" start="0.038" width="0.001" count="1" />
        <bin index="39" start="0.039" width="0.001" count="1" />
        <bin index="40" start="0.04" width="0.001" count="1" />
        <bin index="41" start="0.041" width="0.001" count="1" />
        <bin index="42" start="0.042" width="0.001" count="1" />
        <bin index="43" start="0.043" width="0.001" count="1" />
        <bin index="46" start="0.046" width="0.001" count="1" />
        <bin index="48" start="0.048" width="0.001" count="1" />
        <bin index="51" start="0.051" width="0.001" count="1" />
        <bin index="52" start="0.052" width="0.001" count="1" />
        <bin index="54" start="0.054" width="0.001" count="1" />
        <bin index="55" start="0.055" width="0.001" count="1" />
        <bin index="60" start="0.06" width="0.001" count="1" />
        <bin index="62" start="0.062" width="0.001" count="2" />
        <bin index="66" start="0.066" width="0.001" count="1" />
        <bin index="75" start="0.075" width="0.001" count="1" />
        <bin index="76" start="0.076" width="0.001" count="1" />
        <bin index="79" start="0.079" width="0.001" count="1" />
        <bin index="80" start="0.08" width="0.001" count="1" />
        <bin index="84" start="0.084" width="0.001" count="1" />
        <bin index="85" start="0.085" width="0.001" count="1" />
        <bin index="95" start="0.095" width="0.001" count="2" />
        <bin index="96" start="0.096" width="0.001" count="1" />
        <bin index="105" start="0.105" width="0.001" count="1" />
        <bin index="106" start="0.106" width="0.001" count="1" />
        <bin index="133" start="0.133" width="0.001" count="1" />
        <bin index="385" start="0.385" width="0.001" count="1" />
      </jitterHistogram>
      <packetSizeHistogram nBins="28" >
        <bin index="27" start="540" width="20" count="2330" />
      </packetSizeHistogram>
      <flowInterruptionsHistogram nBins="28" >
        <bin index="7" start="1.75" width="0.25" count="1" />
        <bin index="11" start="2.75" width="0.25" count="1" />
        <bin index="16" start="4" width="0.25" count="1" />
        <bin index="27" start="6.75" width="0.25" count="1" />
      </flowInterruptionsHistogram>
    </Flow>
    <Flow flowId="2" timeFirstTxPacket="+4.63971e+10ns" timeFirstRxPacket="+4.64177e+10ns" timeLastTxPacket="+6.99982e+10ns" timeLastRxPacket="+6.99989e+10ns" delaySum="+5.20299e+09ns" jitterSum="+8.6964e+07ns" lastDelay="+661158ns" maxDelay="+2.06246e+07ns" minDelay="+633379ns" txBytes="3112020" rxBytes="3111480" txPackets="5763" rxPackets="5762" lostPackets="1" timesForwarded="1452">
      <delayHistogram nBins="21" >
        <bin index="0" start="0" width="0.001" count="4291" />
        <bin index="1" start="0.001" width="0.001" count="1453" />
        <bin index="2" start="0.002" width="0.001" count="4" />
        <bin index="3" start="0.003" width="0.001" count="5" />
        <bin index="5" start="0.005" width="0.001" count="1" />
        <bin index="6" start="0.006" width="0.001" count="1" />
        <bin index="7" start="0.007" width="0.001" count="1" />
        <bin index="9" start="0.009" width="0.001" count="2" />
        <bin index="12" start="0.012" width="0.001" count="1" />
        <bin index="16" start="0.016" width="0.001" count="1" />
        <bin index="18" start="0.018" width="0.001" count="1" />
        <bin index="20" start="0.02" width="0.001" count="1" />
      </delayHistogram>
      <jitterHistogram nBins="11" >
        <bin index="0" start="0" width="0.001" count="5731" />
        <bin index="1" start="0.001" width="0.001" count="16" />
        <bin index="2" start="0.002" width="0.001" count="11" />
        <bin index="3" start="0.003" width="0.001" count="1" />
        <bin index="7" start="0.007" width="0.001" count="1" />
        <bin index="10" start="0.01" width="0.001" count="1" />
      </jitterHistogram>
      <packetSizeHistogram nBins="28" >
        <bin index="27" start="540" width="20" count="5762" />
      </packetSizeHistogram>
      <flowInterruptionsHistogram nBins="0" >
      </flowInterruptionsHistogram>
    </Flow>
  </FlowStats>
  <Ipv4FlowClassifier>
    <Flow flowId="2" sourceAddress="10.0.0.1" destinationAddress="10.0.0.20" protocol="17" sourcePort="49153" destinationPort="9000">
      <Dscp value="0x0" packets="5763" />
    </Flow>
    <Flow flowId="1" sourceAddress="10.0.0.2" destinationAddress="10.0.0.19" protocol="17" sourcePort="49153" destinationPort="9001">
      <Dscp value="0x0" packets="6438" />
    </Flow>
  </Ipv4FlowClassifier>
  <Ipv6FlowClassifier>
  </Ipv6FlowClassifier>
  <FlowProbes>
    <FlowProbe index="0">
      <FlowStats  flowId="2" packets="5763" bytes="3112020" delayFromFirstProbeSum="+0ns" >
      </FlowStats>
    </FlowProbe>
    <FlowProbe index="1">
    </FlowProbe>
    <FlowProbe index="2">
      <FlowStats  flowId="1" packets="6438" bytes="3476520" delayFromFirstProbeSum="+0ns" >
      </FlowStats>
    </FlowProbe>
    <FlowProbe index="3">
    </FlowProbe>
    <FlowProbe index="4">
      <FlowStats  flowId="2" packets="1453" bytes="784620" delayFromFirstProbeSum="+9.8678e+08ns" >
      </FlowStats>
    </FlowProbe>
    <FlowProbe index="5">
    </FlowProbe>
    <FlowProbe index="6">
      <FlowStats  flowId="1" packets="243" bytes="131220" delayFromFirstProbeSum="+1.08499e+11ns" >
      </FlowStats>
    </FlowProbe>
    <FlowProbe index="7">
    </FlowProbe>
    <FlowProbe index="8">
    </FlowProbe>
    <FlowProbe index="9">
    </FlowProbe>
    <FlowProbe index="10">
    </FlowProbe>
    <FlowProbe index="11">
    </FlowProbe>
    <FlowProbe index="12">
    </FlowProbe>
    <FlowProbe index="13">
    </FlowProbe>
    <FlowProbe index="14">
      <FlowStats  flowId="1" packets="2767" bytes="1494180" delayFromFirstProbeSum="+8.88823e+11ns" >
      </FlowStats>
    </FlowProbe>
    <FlowProbe index="15">
    </FlowProbe>
    <FlowProbe index="16">
    </FlowProbe>
    <FlowProbe index="17">
    </FlowProbe>
    <FlowProbe index="18">
    </FlowProbe>
    <FlowProbe index="19">
    </FlowProbe>
    <FlowProbe index="20">
    </FlowProbe>
    <FlowProbe index="21">
    </FlowProbe>
    <FlowProbe index="22">
    </FlowProbe>
    <FlowProbe index="23">
    </FlowProbe>
    <FlowProbe index="24">
      <FlowStats  flowId="1" packets="295" bytes="159300" delayFromFirstProbeSum="+1.14037e+10ns" >
      </FlowStats>
    </FlowProbe>
    <FlowProbe index="25">
    </FlowProbe>
    <FlowProbe index="26">
    </FlowProbe>
    <FlowProbe index="27">
    </FlowProbe>
    <FlowProbe index="28">
      <FlowStats  flowId="1" packets="2942" bytes="1588680" delayFromFirstProbeSum="+8.46411e+11ns" >
        <packetsDropped reasonCode="0" number="30" />
        <bytesDropped reasonCode="0" bytes="16200" />
      </FlowStats>
    </FlowProbe>
    <FlowProbe index="29">
    </FlowProbe>
    <FlowProbe index="30">
      <FlowStats  flowId="1" packets="884" bytes="477360" delayFromFirstProbeSum="+3.21389e+11ns" >
      </FlowStats>
    </FlowProbe>
    <FlowProbe index="31">
    </FlowProbe>
    <FlowProbe index="32">
    </FlowProbe>
    <FlowProbe index="33">
    </FlowProbe>
    <FlowProbe index="34">
    </FlowProbe>
    <FlowProbe index="35">
    </FlowProbe>
    <FlowProbe index="36">
      <FlowStats  flowId="1" packets="2330" bytes="1258200" delayFromFirstProbeSum="+7.21819e+11ns" >
      </FlowStats>
    </FlowProbe>
    <FlowProbe index="37">
    </FlowProbe>
    <FlowProbe index="38">
      <FlowStats  flowId="2" packets="5762" bytes="3111480" delayFromFirstProbeSum="+5.20299e+09ns" >
      </FlowStats>
    </FlowProbe>
    <FlowProbe index="39">
    </FlowProbe>
  </FlowProbes>
</FlowMonitor>
