<?xml version="1.0" ?>
<FlowMonitor>
  <FlowStats>
    <Flow flowId="1" timeFirstTxPacket="+2.01949e+10ns" timeFirstRxPacket="+2.02384e+10ns" timeLastTxPacket="+3.05455e+10ns" timeLastRxPacket="+2.37367e+10ns" delaySum="+2.46059e+11ns" jitterSum="+3.32599e+09ns" lastDelay="+1.00638e+09ns" maxDelay="+1.27775e+09ns" minDelay="+4.31964e+07ns" txBytes="1124820" rxBytes="186300" txPackets="2083" rxPackets="345" lostPackets="1738" timesForwarded="1035">
      <packetsDropped reasonCode="0" number="646" />
      <bytesDropped reasonCode="0" bytes="348840" />
      <delayHistogram nBins="1278" >
        <bin index="43" start="0.043" width="0.001" count="2" />
        <bin index="46" start="0.046" width="0.001" count="1" />
        <bin index="54" start="0.054" width="0.001" count="1" />
        <bin index="71" start="0.071" width="0.001" count="1" />
        <bin index="73" start="0.073" width="0.001" count="1" />
        <bin index="81" start="0.081" width="0.001" count="1" />
        <bin index="109" start="0.109" width="0.001" count="1" />
        <bin index="110" start="0.11" width="0.001" count="1" />
        <bin index="113" start="0.113" width="0.001" count="1" />
        <bin index="114" start="0.114" width="0.001" count="1" />
        <bin index="116" start="0.116" width="0.001" count="1" />
        <bin index="118" start="0.118" width="0.001" count="1" />
        <bin index="120" start="0.12" width="0.001" count="1" />
        <bin index="122" start="0.122" width="0.001" count="1" />
        <bin index="125" start="0.125" width="0.001" count="3" />
        <bin index="126" start="0.126" width="0.001" count="1" />
        <bin index="128" start="0.128" width="0.001" count="1" />
        <bin index="130" start="0.13" width="0.001" count="1" />
        <bin index="133" start="0.133" width="0.001" count="2" />
        <bin index="134" start="0.134" width="0.001" count="1" />
        <bin index="135" start="0.135" width="0.001" count="1" />
        <bin index="137" start="0.137" width="0.001" count="3" />
        <bin index="140" start="0.14" width="0.001" count="2" />
        <bin index="143" start="0.143" width="0.001" count="2" />
        <bin index="144" start="0.144" width="0.001" count="1" />
        <bin index="146" start="0.146" width="0.001" count="1" />
        <bin index="149" start="0.149" width="0.001" count="1" />
        <bin index="152" start="0.152" width="0.001" count="1" />
        <bin index="163" start="0.163" width="0.001" count="1" />
        <bin index="165" start="0.165" width="0.001" count="1" />
        <bin index="169" start="0.169" width="0.001" count="2" />
        <bin index="172" start="0.172" width="0.001" count="2" />
        <bin index="174" start="0.174" width="0.001" count="1" />
        <bin index="177" start="0.177" width="0.001" count="1" />
        <bin index="179" start="0.179" width="0.001" count="1" />
        <bin index="185" start="0.185" width="0.001" count="1" />
        <bin index="195" start="0.195" width="0.001" count="1" />
        <bin index="196" start="0.196" width="0.001" count="1" />
        <bin index="255" start="0.255" width="0.001" count="1" />
        <bin index="256" start="0.256" width="0.001" count="1" />
        <bin index="259" start="0.259" width="0.001" count="1" />
        <bin index="260" start="0.26" width="0.001" count="1" />
        <bin index="261" start="0.261" width="0.001" count="1" />
        <bin index="263" start="0.263" width="0.001" count="1" />
        <bin index="264" start="0.264" width="0.001" count="1" />
        <bin index="266" start="0.266" width="0.001" count="1" />
        <bin index="268" start="0.268" width="0.001" count="1" />
        <bin index="297" start="0.297" width="0.001" count="1" />
        <bin index="298" start="0.298" width="0.001" count="1" />
        <bin index="301" start="0.301" width="0.001" count="1" />
        <bin index="305" start="0.305" width="0.001" count="1" />
        <bin index="306" start="0.306" width="0.001" count="1" />
        <bin index="307" start="0.307" width="0.001" count="1" />
        <bin index="308" start="0.308" width="0.001" count="1" />
        <bin index="310" start="0.31" width="0.001" count="2" />
        <bin index="312" start="0.312" width="0.001" count="1" />
        <bin index="315" start="0.315" width="0.001" count="1" />
        <bin index="317" start="0.317" width="0.001" count="1" />
        <bin index="318" start="0.318" width="0.001" count="1" />
        <bin index="321" start="0.321" width="0.001" count="1" />
        <bin index="324" start="0.324" width="0.001" count="1" />
        <bin index="327" start="0.327" width="0.001" count="1" />
        <bin index="330" start="0.33" width="0.001" count="1" />
        <bin index="333" start="0.333" width="0.001" count="1" />
        <bin index="336" start="0.336" width="0.001" count="1" />
        <bin index="339" start="0.339" width="0.001" count="1" />
        <bin index="343" start="0.343" width="0.001" count="1" />
        <bin index="345" start="0.345" width="0.001" count="1" />
        <bin index="348" start="0.348" width="0.001" count="1" />
        <bin index="349" start="0.349" width="0.001" count="1" />
        <bin index="350" start="0.35" width="0.001" count="1" />
        <bin index="352" start="0.352" width="0.001" count="1" />
        <bin index="354" start="0.354" width="0.001" count="2" />
        <bin index="356" start="0.356" width="0.001" count="1" />
        <bin index="357" start="0.357" width="0.001" count="1" />
        <bin index="359" start="0.359" width="0.001" count="1" />
        <bin index="361" start="0.361" width="0.001" count="1" />
        <bin index="403" start="0.403" width="0.001" count="1" />
        <bin index="404" start="0.404" width="0.001" count="1" />
        <bin index="407" start="0.407" width="0.001" count="3" />
        <bin index="409" start="0.409" width="0.001" count="1" />
        <bin index="410" start="0.41" width="0.001" count="2" />
        <bin index="413" start="0.413" width="0.001" count="2" />
        <bin index="414" start="0.414" width="0.001" count="2" />
        <bin index="416" start="0.416" width="0.001" count="1" />
        <bin index="417" start="0.417" width="0.001" count="2" />
        <bin index="418" start="0.418" width="0.001" count="2" />
        <bin index="420" start="0.42" width="0.001" count="1" />
        <bin index="461" start="0.461" width="0.001" count="1" />
        <bin index="464" start="0.464" width="0.001" count="2" />
        <bin index="467" start="0.467" width="0.001" count="1" />
        <bin index="469" start="0.469" width="0.001" count="2" />
        <bin index="470" start="0.47" width="0.001" count="1" />
        <bin index="515" start="0.515" width="0.001" count="1" />
        <bin index="517" start="0.517" width="0.001" count="1" />
        <bin index="570" start="0.57" width="0.001" count="2" />
        <bin index="571" start="0.571" width="0.001" count="1" />
        <bin index="572" start="0.572" width="0.001" count="1" />
        <bin index="574" start="0.574" width="0.001" count="1" />
        <bin index="575" start="0.575" width="0.001" count="1" />
        <bin index="582" start="0.582" width="0.001" count="1" />
        <bin index="584" start="0.584" width="0.001" count="1" />
        <bin index="587" start="0.587" width="0.001" count="1" />
        <bin index="594" start="0.594" width="0.001" count="1" />
        <bin index="633" start="0.633" width="0.001" count="1" />
        <bin index="666" start="0.666" width="0.001" count="1" />
        <bin index="669" start="0.669" width="0.001" count="1" />
        <bin index="688" start="0.688" width="0.001" count="1" />
        <bin index="691" start="0.691" width="0.001" count="1" />
        <bin index="694" start="0.694" width="0.001" count="1" />
        <bin index="696" start="0.696" width="0.001" count="2" />
        <bin index="699" start="0.699" width="0.001" count="1" />
        <bin index="702" start="0.702" width="0.001" count="1" />
        <bin index="703" start="0.703" width="0.001" count="1" />
        <bin index="705" start="0.705" width="0.001" count="1" />
        <bin index="710" start="0.71" width="0.001" count="1" />
        <bin index="712" start="0.712" width="0.001" count="1" />
        <bin index="713" start="0.713" width="0.001" count="1" />
        <bin index="714" start="0.714" width="0.001" count="1" />
        <bin index="715" start="0.715" width="0.001" count="1" />
        <bin index="716" start="0.716" width="0.001" count="1" />
        <bin index="717" start="0.717" width="0.001" count="1" />
        <bin index="718" start="0.718" width="0.001" count="2" />
        <bin index="719" start="0.719" width="0.001" count="2" />
        <bin index="720" start="0.72" width="0.001" count="1" />
        <bin index="721" start="0.721" width="0.001" count="2" />
        <bin index="722" start="0.722" width="0.001" count="3" />
        <bin index="725" start="0.725" width="0.001" count="1" />
        <bin index="727" start="0.727" width="0.001" count="1" />
        <bin index="731" start="0.731" width="0.001" count="1" />
        <bin index="733" start="0.733" width="0.001" count="1" />
        <bin index="736" start="0.736" width="0.001" count="1" />
        <bin index="820" start="0.82" width="0.001" count="1" />
        <bin index="822" start="0.822" width="0.001" count="2" />
        <bin index="823" start="0.823" width="0.001" count="2" />
        <bin index="825" start="0.825" width="0.001" count="1" />
        <bin index="854" start="0.854" width="0.001" count="1" />
        <bin index="862" start="0.862" width="0.001" count="1" />
        <bin index="865" start="0.865" width="0.001" count="1" />
        <bin index="901" start="0.901" width="0.001" count="1" />
        <bin index="902" start="0.902" width="0.001" count="1" />
        <bin index="904" start="0.904" width="0.001" count="1" />
        <bin index="909" start="0.909" width="0.001" count="1" />
        <bin index="911" start="0.911" width="0.001" count="1" />
        <bin index="912" start="0.912" width="0.001" count="1" />
        <bin index="917" start="0.917" width="0.001" count="1" />
        <bin index="919" start="0.919" width="0.001" count="1" />
        <bin index="921" start="0.921" width="0.001" count="2" />
        <bin index="922" start="0.922" width="0.001" count="1" />
        <bin index="924" start="0.924" width="0.001" count="2" />
        <bin index="925" start="0.925" width="0.001" count="1" />
        <bin index="927" start="0.927" width="0.001" count="1" />
        <bin index="929" start="0.929" width="0.001" count="1" />
        <bin index="930" start="0.93" width="0.001" count="1" />
        <bin index="932" start="0.932" width="0.001" count="2" />
        <bin index="933" start="0.933" width="0.001" count="1" />
        <bin index="935" start="0.935" width="0.001" count="1" />
        <bin index="937" start="0.937" width="0.001" count="1" />
        <bin index="941" start="0.941" width="0.001" count="1" />
        <bin index="944" start="0.944" width="0.001" count="1" />
        <bin index="945" start="0.945" width="0.001" count="1" />
        <bin index="947" start="0.947" width="0.001" count="1" />
        <bin index="949" start="0.949" width="0.001" count="1" />
        <bin index="950" start="0.95" width="0.001" count="1" />
        <bin index="952" start="0.952" width="0.001" count="1" />
        <bin index="955" start="0.955" width="0.001" count="2" />
        <bin index="957" start="0.957" width="0.001" count="1" />
        <bin index="958" start="0.958" width="0.001" count="2" />
        <bin index="959" start="0.959" width="0.001" count="2" />
        <bin index="960" start="0.96" width="0.001" count="2" />
        <bin index="961" start="0.961" width="0.001" count="4" />
        <bin index="962" start="0.962" width="0.001" count="4" />
        <bin index="963" start="0.963" width="0.001" count="1" />
        <bin index="964" start="0.964" width="0.001" count="3" />
        <bin index="965" start="0.965" width="0.001" count="2" />
        <bin index="966" start="0.966" width="0.001" count="1" />
        <bin index="967" start="0.967" width="0.001" count="3" />
        <bin index="968" start="0.968" width="0.001" count="8" />
        <bin index="970" start="0.97" width="0.001" count="1" />
        <bin index="971" start="0.971" width="0.001" count="1" />
        <bin index="973" start="0.973" width="0.001" count="3" />
        <bin index="974" start="0.974" width="0.001" count="2" />
        <bin index="975" start="0.975" width="0.001" count="1" />
        <bin index="976" start="0.976" width="0.001" count="2" />
        <bin index="977" start="0.977" width="0.001" count="3" />
        <bin index="978" start="0.978" width="0.001" count="1" />
        <bin index="979" start="0.979" width="0.001" count="1" />
        <bin index="980" start="0.98" width="0.001" count="2" />
        <bin index="981" start="0.981" width="0.001" count="2" />
        <bin index="982" start="0.982" width="0.001" count="1" />
        <bin index="984" start="0.984" width="0.001" count="3" />
        <bin index="985" start="0.985" width="0.001" count="1" />
        <bin index="987" start="0.987" width="0.001" count="2" />
        <bin index="989" start="0.989" width="0.001" count="1" />
        <bin index="990" start="0.99" width="0.001" count="1" />
        <bin index="992" start="0.992" width="0.001" count="2" />
        <bin index="993" start="0.993" width="0.001" count="2" />
        <bin index="994" start="0.994" width="0.001" count="1" />
        <bin index="996" start="0.996" width="0.001" count="1" />
        <bin index="997" start="0.997" width="0.001" count="2" />
        <bin index="998" start="0.998" width="0.001" count="1" />
        <bin index="999" start="0.999" width="0.001" count="3" />
        <bin index="1000" start="1" width="0.001" count="1" />
        <bin index="1001" start="1.001" width="0.001" count="1" />
        <bin index="1002" start="1.002" width="0.001" count="2" />
        <bin index="1003" start="1.003" width="0.001" count="1" />
        <bin index="1005" start="1.005" width="0.001" count="1" />
        <bin index="1006" start="1.006" width="0.001" count="2" />
        <bin index="1008" start="1.008" width="0.001" count="1" />
        <bin index="1014" start="1.014" width="0.001" count="1" />
        <bin index="1018" start="1.018" width="0.001" count="1" />
        <bin index="1019" start="1.019" width="0.001" count="1" />
        <bin index="1021" start="1.021" width="0.001" count="1" />
        <bin index="1022" start="1.022" width="0.001" count="2" />
        <bin index="1023" start="1.023" width="0.001" count="2" />
        <bin index="1025" start="1.025" width="0.001" count="4" />
        <bin index="1028" start="1.028" width="0.001" count="1" />
        <bin index="1041" start="1.041" width="0.001" count="1" />
        <bin index="1049" start="1.049" width="0.001" count="1" />
        <bin index="1050" start="1.05" width="0.001" count="1" />
        <bin index="1051" start="1.051" width="0.001" count="3" />
        <bin index="1053" start="1.053" width="0.001" count="1" />
        <bin index="1054" start="1.054" width="0.001" count="3" />
        <bin index="1055" start="1.055" width="0.001" count="1" />
        <bin index="1056" start="1.056" width="0.001" count="2" />
        <bin index="1058" start="1.058" width="0.001" count="2" />
        <bin index="1067" start="1.067" width="0.001" count="1" />
        <bin index="1070" start="1.07" width="0.001" count="1" />
        <bin index="1081" start="1.081" width="0.001" count="1" />
        <bin index="1084" start="1.084" width="0.001" count="1" />
        <bin index="1091" start="1.091" width="0.001" count="1" />
        <bin index="1093" start="1.093" width="0.001" count="1" />
        <bin index="1098" start="1.098" width="0.001" count="1" />
        <bin index="1099" start="1.099" width="0.001" count="1" />
        <bin index="1101" start="1.101" width="0.001" count="1" />
        <bin index="1110" start="1.11" width="0.001" count="1" />
        <bin index="1111" start="1.111" width="0.001" count="2" />
        <bin index="1114" start="1.114" width="0.001" count="2" />
        <bin index="1115" start="1.115" width="0.001" count="1" />
        <bin index="1116" start="1.116" width="0.001" count="2" />
        <bin index="1117" start="1.117" width="0.001" count="1" />
        <bin index="1118" start="1.118" width="0.001" count="2" />
        <bin index="1120" start="1.12" width="0.001" count="1" />
        <bin index="1122" start="1.122" width="0.001" count="2" />
        <bin index="1124" start="1.124" width="0.001" count="1" />
        <bin index="1128" start="1.128" width="0.001" count="2" />
        <bin index="1137" start="1.137" width="0.001" count="1" />
        <bin index="1146" start="1.146" width="0.001" count="1" />
        <bin index="1154" start="1.154" width="0.001" count="1" />
        <bin index="1185" start="1.185" width="0.001" count="1" />
        <bin index="1186" start="1.186" width="0.001" count="1" />
        <bin index="1187" start="1.187" width="0.001" count="1" />
        <bin index="1189" start="1.189" width="0.001" count="1" />
        <bin index="1241" start="1.241" width="0.001" count="1" />
        <bin index="1277" start="1.277" width="0.001" count="1" />
      </delayHistogram>
      <jitterHistogram nBins="150" >
        <bin index="0" start="0" width="0.001" count="38" />
        <bin index="1" start="0.001" width="0.001" count="62" />
        <bin index="2" start="0.002" width="0.001" count="110" />
        <bin index="3" start="0.003" width="0.001" count="32" />
        <bin index="4" start="0.004" width="0.001" count="4" />
        <bin index="5" start="0.005" width="0.001" count="7" />
        <bin index="6" start="0.006" width="0.001" count="5" />
        <bin index="7" start="0.007" width="0.001" count="4" />
        <bin index="8" start="0.008" width="0.001" count="3" />
        <bin index="9" start="0.009" width="0.001" count="6" />
        <bin index="10" start="0.01" width="0.001" count="6" />
        <bin index="11" start="0.011" width="0.001" count="4" />
        <bin index="12" start="0.012" width="0.001" count="2" />
        <bin index="13" start="0.013" width="0.001" count="2" />
        <bin index="14" start="0.014" width="0.001" count="1" />
        <bin index="15" start="0.015" width="0.001" count="3" />
        <bin index="16" start="0.016" width="0.001" count="3" />
        <bin index="17" start="0.017" width="0.001" count="2" />
        <bin index="20" start="0.02" width="0.001" count="1" />
        <bin index="21" start="0.021" width="0.001" count="1" />
        <bin index="22" start="0.022" width="0.001" count="2" />
        <bin index="23" start="0.023" width="0.001" count="3" />
        <bin index="24" start="0.024" width="0.001" count="3" />
        <bin index="25" start="0.025" width="0.001" count="1" />
        <bin index="26" start="0.026" width="0.001" count="1" />
        <bin index="27" start="0.027" width="0.001" count="2" />
        <bin index="28" start="0.028" width="0.001" count="1" />
        <bin index="29" start="0.029" width="0.001" count="1" />
        <bin index="30" start="0.03" width="0.001" count="1" />
        <bin index="32" start="0.032" width="0.001" count="1" />
        <bin index="33" start="0.033" width="0.001" count="1" />
        <bin index="35" start="0.035" width="0.001" count="2" />
        <bin index="36" start="0.036" width="0.001" count="1" />
        <bin index="37" start="0.037" width="0.001" count="1" />
        <bin index="41" start="0.041" width="0.001" count="4" />
        <bin index="43" start="0.043" width="0.001" count="1" />
        <bin index="46" start="0.046" width="0.001" count="1" />
        <bin index="47" start="0.047" width="0.001" count="1" />
        <bin index="48" start="0.048" width="0.001" count="3" />
        <bin index="51" start="0.051" width="0.001" count="1" />
        <bin index="52" start="0.052" width="0.001" count="1" />
        <bin index="53" start="0.053" width="0.001" count="1" />
        <bin index="54" start="0.054" width="0.001" count="1" />
        <bin index="55" start="0.055" width="0.001" count="1" />
        <bin index="59" start="0.059" width="0.001" count="1" />
        <bin index="61" start="0.061" width="0.001" count="1" />
        <bin index="62" start="0.062" width="0.001" count="2" />
        <bin index="63" start="0.063" width="0.001" count="1" />
        <bin index="66" start="0.066" width="0.001" count="2" />
        <bin index="72" start="0.072" width="0.001" count="1" />
        <bin index="84" start="0.084" width="0.001" count="1" />
        <bin index="97" start="0.097" width="0.001" count="1" />
        <bin index="105" start="0.105" width="0.001" count="1" />
        <bin index="149" start="0.149" width="0.001" count="1" />
      </jitterHistogram>
      <packetSizeHistogram nBins="28" >
        <bin index="27" start="540" width="20" count="345" />
      </packetSizeHistogram>
      <flowInterruptionsHistogram nBins="0" >
      </flowInterruptionsHistogram>
    </Flow>
  </FlowStats>
  <Ipv4FlowClassifier>
    <Flow flowId="1" sourceAddress="10.0.0.2" destinationAddress="10.0.0.19" protocol="17" sourcePort="49153" destinationPort="9001">
      <Dscp value="0x0" packets="2083" />
    </Flow>
  </Ipv4FlowClassifier>
  <Ipv6FlowClassifier>
  </Ipv6FlowClassifier>
  <FlowProbes>
    <FlowProbe index="0">
    </FlowProbe>
    <FlowProbe index="1">
    </FlowProbe>
    <FlowProbe index="2">
      <FlowStats  flowId="1" packets="2083" bytes="1124820" delayFromFirstProbeSum="+0ns" >
      </FlowStats>
    </FlowProbe>
    <FlowProbe index="3">
    </FlowProbe>
    <FlowProbe index="4">
    </FlowProbe>
    <FlowProbe index="5">
    </FlowProbe>
    <FlowProbe index="6">
    </FlowProbe>
    <FlowProbe index="7">
    </FlowProbe>
    <FlowProbe index="8">
    </FlowProbe>
    <FlowProbe index="9">
    </FlowProbe>
    <FlowProbe index="10">
    </FlowProbe>
    <FlowProbe index="11">
    </FlowProbe>
    <FlowProbe index="12">
      <FlowStats  flowId="1" packets="436" bytes="235440" delayFromFirstProbeSum="+2.12344e+11ns" >
      </FlowStats>
    </FlowProbe>
    <FlowProbe index="13">
    </FlowProbe>
    <FlowProbe index="14">
    </FlowProbe>
    <FlowProbe index="15">
    </FlowProbe>
    <FlowProbe index="16">
      <FlowStats  flowId="1" packets="1441" bytes="778140" delayFromFirstProbeSum="+3.6007e+10ns" >
        <packetsDropped reasonCode="0" number="630" />
        <bytesDropped reasonCode="0" bytes="340200" />
      </FlowStats>
    </FlowProbe>
    <FlowProbe index="17">
    </FlowProbe>
    <FlowProbe index="18">
    </FlowProbe>
    <FlowProbe index="19">
    </FlowProbe>
    <FlowProbe index="20">
    </FlowProbe>
    <FlowProbe index="21">
    </FlowProbe>
    <FlowProbe index="22">
    </FlowProbe>
    <FlowProbe index="23">
    </FlowProbe>
    <FlowProbe index="24">
    </FlowProbe>
    <FlowProbe index="25">
    </FlowProbe>
    <FlowProbe index="26">
    </FlowProbe>
    <FlowProbe index="27">
    </FlowProbe>
    <FlowProbe index="28">
    </FlowProbe>
    <FlowProbe index="29">
    </FlowProbe>
    <FlowProbe index="30">
    </FlowProbe>
    <FlowProbe index="31">
    </FlowProbe>
    <FlowProbe index="32">
      <FlowStats  flowId="1" packets="1410" bytes="761400" delayFromFirstProbeSum="+2.17384e+11ns" >
        <packetsDropped reasonCode="0" number="16" />
        <bytesDropped reasonCode="0" bytes="8640" />
      </FlowStats>
    </FlowProbe>
    <FlowProbe index="33">
    </FlowProbe>
    <FlowProbe index="34">
    </FlowProbe>
    <FlowProbe index="35">
    </FlowProbe>
    <FlowProbe index="36">
      <FlowStats  flowId="1" packets="345" bytes="186300" delayFromFirstProbeSum="+2.46059e+11ns" >
      </FlowStats>
    </FlowProbe>
    <FlowProbe index="37">
    </FlowProbe>
    <FlowProbe index="38">
    </FlowProbe>
    <FlowProbe index="39">
    </FlowProbe>
  </FlowProbes>
</FlowMonitor>
