<?xml version="1.0" ?>
<FlowMonitor>
  <FlowStats>
    <Flow flowId="1" timeFirstTxPacket="+5.23199e+10ns" timeFirstRxPacket="+5.23497e+10ns" timeLastTxPacket="+6.99982e+10ns" timeLastRxPacket="+6.99989e+10ns" delaySum="+1.40126e+10ns" jitterSum="+2.9869e+09ns" lastDelay="+661131ns" maxDelay="+6.28413e+07ns" minDelay="+624819ns" txBytes="2331180" rxBytes="2325780" txPackets="4317" rxPackets="4307" lostPackets="3" timesForwarded="978">
      <delayHistogram nBins="63" >
        <bin index="0" start="0" width="0.001" count="2555" />
        <bin index="1" start="0.001" width="0.001" count="1130" />
        <bin index="2" start="0.002" width="0.001" count="65" />
        <bin index="3" start="0.003" width="0.001" count="39" />
        <bin index="4" start="0.004" width="0.001" count="44" />
        <bin index="5" start="0.005" width="0.001" count="23" />
        <bin index="6" start="0.006" width="0.001" count="27" />
        <bin index="7" start="0.007" width="0.001" count="21" />
        <bin index="8" start="0.008" width="0.001" count="19" />
        <bin index="9" start="0.009" width="0.001" count="17" />
        <bin index="10" start="0.01" width="0.001" count="26" />
        <bin index="11" start="0.011" width="0.001" count="14" />
        <bin index="12" start="0.012" width="0.001" count="11" />
        <bin index="13" start="0.013" width="0.001" count="18" />
        <bin index="14" start="0.014" width="0.001" count="13" />
        <bin index="15" start="0.015" width="0.001" count="12" />
        <bin index="16" start="0.016" width="0.001" count="20" />
        <bin index="17" start="0.017" width="0.001" count="11" />
        <bin index="18" start="0.018" width="0.001" count="8" />
        <bin index="19" start="0.019" width="0.001" count="19" />
        <bin index="20" start="0.02" width="0.001" count="11" />
        <bin index="21" start="0.021" width="0.001" count="12" />
        <bin index="22" start="0.022" width="0.001" count="17" />
        <bin index="23" start="0.023" width="0.001" count="5" />
        <bin index="24" start="0.024" width="0.001" count="7" />
        <bin index="25" start="0.025" width="0.001" count="17" />
        <bin index="26" start="0.026" width="0.001" count="5" />
        <bin index="27" start="0.027" width="0.001" count="8" />
        <bin index="28" start="0.028" width="0.001" count="11" />
        <bin index="29" start="0.029" width="0.001" count="7" />
        <bin index="30" start="0.03" width="0.001" count="4" />
        <bin index="31" start="0.031" width="0.001" count="9" />
        <bin index="32" start="0.032" width="0.001" count="10" />
        <bin index="33" start="0.033" width="0.001" count="5" />
        <bin index="34" start="0.034" width="0.001" count="6" />
        <bin index="35" start="0.035" width="0.001" count="7" />
        <bin index="36" start="0.036" width="0.001" count="3" />
        <bin index="37" start="0.037" width="0.001" count="8" />
        <bin index="38" start="0.038" width="0.001" count="5" />
        <bin index="39" start="0.039" width="0.001" count="5" />
        <bin index="40" start="0.04" width="0.001" count="5" />
        <bin index="41" start="0.041" width="0.001" count="6" />
        <bin index="42" start="0.042" width="0.001" count="3" />
        <bin index="43" start="0.043" width="0.001" count="3" />
        <bin index="44" start="0.044" width="0.001" count="5" />
        <bin index="45" start="0.045" width="0.001" count="3" />
        <bin index="46" start="0.046" width="0.001" count="7" />
        <bin index="47" start="0.047" width="0.001" count="3" />
        <bin index="48" start="0.048" width="0.001" count="1" />
        <bin index="49" start="0.049" width="0.001" count="2" />
        <bin index="50" start="0.05" width="0.001" count="3" />
        <bin index="52" start="0.052" width="0.001" count="3" />
        <bin index="53" start="0.053" width="0.001" count="3" />
        <bin index="55" start="0.055" width="0.001" count="1" />
        <bin index="56" start="0.056" width="0.001" count="1" />
        <bin index="58" start="0.058" width="0.001" count="1" />
        <bin index="59" start="0.059" width="0.001" count="1" />
        <bin index="61" start="0.061" width="0.001" count="1" />
        <bin index="62" start="0.062" width="0.001" count="1" />
      </delayHistogram>
      <jitterHistogram nBins="53" >
        <bin index="0" start="0" width="0.001" count="3577" />
        <bin index="1" start="0.001" width="0.001" count="126" />
        <bin index="2" start="0.002" width="0.001" count="323" />
        <bin index="3" start="0.003" width="0.001" count="180" />
        <bin index="4" start="0.004" width="0.001" count="22" />
        <bin index="5" start="0.005" width="0.001" count="14" />
        <bin index="6" start="0.006" width="0.001" count="9" />
        <bin index="7" start="0.007" width="0.001" count="9" />
        <bin index="8" start="0.008" width="0.001" count="9" />
        <bin index="9" start="0.009" width="0.001" count="1" />
        <bin index="10" start="0.01" width="0.001" count="3" />
        <bin index="11" start="0.011" width="0.001" count="2" />
        <bin index="12" start="0.012" width="0.001" count="2" />
        <bin index="13" start="0.013" width="0.001" count="3" />
        <bin index="14" start="0.014" width="0.001" count="2" />
        <bin index="16" start="0.016" width="0.001" count="2" />
        <bin index="17" start="0.017" width="0.001" count="2" />
        <bin index="19" start="0.019" width="0.001" count="2" />
        <bin index="20" start="0.02" width="0.001" count="1" />
        <bin index="21" start="0.021" width="0.001" count="1" />
        <bin index="26" start="0.026" width="0.001" count="3" />
        <bin index="29" start="0.029" width="0.001" count="1" />
        <bin index="31" start="0.031" width="0.001" count="3" />
        <bin index="32" start="0.032" width="0.001" count="2" />
        <bin index="33" start="0.033" width="0.001" count="3" />
        <bin index="39" start="0.039" width="0.001" count="1" />
        <bin index="45" start="0.045" width="0.001" count="1" />
        <bin index="49" start="0.049" width="0.001" count="1" />
        <bin index="52" start="0.052" width="0.001" count="1" />
      </jitterHistogram>
      <packetSizeHistogram nBins="28" >
        <bin index="27" start="540" width="20" count="4307" />
      </packetSizeHistogram>
      <flowInterruptionsHistogram nBins="0" >
      </flowInterruptionsHistogram>
    </Flow>
    <Flow flowId="2" timeFirstTxPacket="+6.43048e+10ns" timeFirstRxPacket="+6.46509e+10ns" timeLastTxPacket="+6.88923e+10ns" timeLastRxPacket="+6.49345e+10ns" delaySum="+1.14202e+10ns" jitterSum="+1.63046e+08ns" lastDelay="+2.89811e+08ns" maxDelay="+2.89811e+08ns" minDelay="+1.83793e+08ns" txBytes="605340" rxBytes="24300" txPackets="1121" rxPackets="45" lostPackets="0" timesForwarded="90">
      <delayHistogram nBins="290" >
        <bin index="183" start="0.183" width="0.001" count="1" />
        <bin index="186" start="0.186" width="0.001" count="1" />
        <bin index="238" start="0.238" width="0.001" count="1" />
        <bin index="242" start="0.242" width="0.001" count="1" />
        <bin index="243" start="0.243" width="0.001" count="1" />
        <bin index="244" start="0.244" width="0.001" count="4" />
        <bin index="245" start="0.245" width="0.001" count="6" />
        <bin index="246" start="0.246" width="0.001" count="4" />
        <bin index="248" start="0.248" width="0.001" count="3" />
        <bin index="249" start="0.249" width="0.001" count="2" />
        <bin index="250" start="0.25" width="0.001" count="2" />
        <bin index="251" start="0.251" width="0.001" count="1" />
        <bin index="253" start="0.253" width="0.001" count="1" />
        <bin index="254" start="0.254" width="0.001" count="2" />
        <bin index="255" start="0.255" width="0.001" count="1" />
        <bin index="256" start="0.256" width="0.001" count="1" />
        <bin index="257" start="0.257" width="0.001" count="2" />
        <bin index="266" start="0.266" width="0.001" count="1" />
        <bin index="272" start="0.272" width="0.001" count="1" />
        <bin index="273" start="0.273" width="0.001" count="1" />
        <bin index="281" start="0.281" width="0.001" count="1" />
        <bin index="282" start="0.282" width="0.001" count="2" />
        <bin index="286" start="0.286" width="0.001" count="1" />
        <bin index="287" start="0.287" width="0.001" count="1" />
        <bin index="288" start="0.288" width="0.001" count="1" />
        <bin index="289" start="0.289" width="0.001" count="2" />
      </delayHistogram>
      <jitterHistogram nBins="55" >
        <bin index="0" start="0" width="0.001" count="18" />
        <bin index="1" start="0.001" width="0.001" count="8" />
        <bin index="2" start="0.002" width="0.001" count="5" />
        <bin index="3" start="0.003" width="0.001" count="3" />
        <bin index="4" start="0.004" width="0.001" count="1" />
        <bin index="5" start="0.005" width="0.001" count="1" />
        <bin index="6" start="0.006" width="0.001" count="3" />
        <bin index="7" start="0.007" width="0.001" count="1" />
        <bin index="9" start="0.009" width="0.001" count="3" />
        <bin index="54" start="0.054" width="0.001" count="1" />
      </jitterHistogram>
      <packetSizeHistogram nBins="28" >
        <bin index="27" start="540" width="20" count="45" />
      </packetSizeHistogram>
      <flowInterruptionsHistogram nBins="0" >
      </flowInterruptionsHistogram>
    </Flow>
  </FlowStats>
  <Ipv4FlowClassifier>
    <Flow flowId="2" sourceAddress="10.0.0.1" destinationAddress="10.0.0.20" protocol="17" sourcePort="49153" destinationPort="9000">
      <Dscp value="0x0" packets="1121" />
    </Flow>
    <Flow flowId="1" sourceAddress="10.0.0.2" destinationAddress="10.0.0.19" protocol="17" sourcePort="49153" destinationPort="9001">
      <Dscp value="0x0" packets="4317" />
    </Flow>
  </Ipv4FlowClassifier>
  <Ipv6FlowClassifier>
  </Ipv6FlowClassifier>
  <FlowProbes>
    <FlowProbe index="0">
      <FlowStats  flowId="2" packets="1121" bytes="605340" delayFromFirstProbeSum="+0ns" >
      </FlowStats>
    </FlowProbe>
    <FlowProbe index="1">
    </FlowProbe>
    <FlowProbe index="2">
      <FlowStats  flowId="1" packets="4317" bytes="2331180" delayFromFirstProbeSum="+0ns" >
      </FlowStats>
    </FlowProbe>
    <FlowProbe index="3">
    </FlowProbe>
    <FlowProbe index="4">
    </FlowProbe>
    <FlowProbe index="5">
    </FlowProbe>
    <FlowProbe index="6">
    </FlowProbe>
    <FlowProbe index="7">
    </FlowProbe>
    <FlowProbe index="8">
    </FlowProbe>
    <FlowProbe index="9">
    </FlowProbe>
    <FlowProbe index="10">
    </FlowProbe>
    <FlowProbe index="11">
    </FlowProbe>
    <FlowProbe index="12">
    </FlowProbe>
    <FlowProbe index="13">
    </FlowProbe>
    <FlowProbe index="14">
    </FlowProbe>
    <FlowProbe index="15">
    </FlowProbe>
    <FlowProbe index="16">
    </FlowProbe>
    <FlowProbe index="17">
    </FlowProbe>
    <FlowProbe index="18">
    </FlowProbe>
    <FlowProbe index="19">
    </FlowProbe>
    <FlowProbe index="20">
      <FlowStats  flowId="1" packets="981" bytes="529740" delayFromFirstProbeSum="+7.14417e+08ns" >
      </FlowStats>
    </FlowProbe>
    <FlowProbe index="21">
    </FlowProbe>
    <FlowProbe index="22">
      <FlowStats  flowId="2" packets="45" bytes="24300" delayFromFirstProbeSum="+1.13305e+10ns" >
      </FlowStats>
    </FlowProbe>
    <FlowProbe index="23">
    </FlowProbe>
    <FlowProbe index="24">
    </FlowProbe>
    <FlowProbe index="25">
    </FlowProbe>
    <FlowProbe index="26">
    </FlowProbe>
    <FlowProbe index="27">
    </FlowProbe>
    <FlowProbe index="28">
    </FlowProbe>
    <FlowProbe index="29">
    </FlowProbe>
    <FlowProbe index="30">
      <FlowStats  flowId="2" packets="1120" bytes="604800" delayFromFirstProbeSum="+3.73962e+10ns" >
      </FlowStats>
    </FlowProbe>
    <FlowProbe index="31">
    </FlowProbe>
    <FlowProbe index="32">
    </FlowProbe>
    <FlowProbe index="33">
    </FlowProbe>
    <FlowProbe index="34">
    </FlowProbe>
    <FlowProbe index="35">
    </FlowProbe>
    <FlowProbe index="36">
      <FlowStats  flowId="1" packets="4307" bytes="2325780" delayFromFirstProbeSum="+1.40126e+10ns" >
      </FlowStats>
    </FlowProbe>
    <FlowProbe index="37">
    </FlowProbe>
    <FlowProbe index="38">
      <FlowStats  flowId="2" packets="45" bytes="24300" delayFromFirstProbeSum="+1.14202e+10ns" >
      </FlowStats>
    </FlowProbe>
    <FlowProbe index="39">
    </FlowProbe>
  </FlowProbes>
</FlowMonitor>
